b3integration_test/__init__.py
b3integration_test/admin.py
b3integration_test/apps.py
b3integration_test/constants.py
b3integration_test/models.py
b3integration_test/seeds.py
b3integration_test/tests.py
b3integration_test/management/__init__.py
b3integration_test/management/commands/__init__.py
b3integration_test/management/commands/test_integration_get_fake_data.py
b3integration_test/migrations/0001_initial.py
b3integration_test/migrations/0002_add_fields_to_settings.py
b3integration_test/migrations/0003_commercialtest_buildingtest.py
b3integration_test/migrations/0004_buildingtest_integration_link_and_more.py
b3integration_test/migrations/0005_remove_buildingtest_integration_and_more.py
b3integration_test/migrations/__init__.py
big3_test_integration-0.1.dev5.dist-info/METADATA
big3_test_integration-0.1.dev5.dist-info/WHEEL
big3_test_integration-0.1.dev5.dist-info/licenses/LICENSE
big3_test_integration-0.1.dev5.dist-info/RECORD
